Metadata-Version: 1.1
Name: nbexec
Version: 0.1.0
Summary: A dead-simple tool for executing Jupyter notebooks from the command line.
Home-page: http://github.com/jsvine/nbexec
Author: Jeremy Singer-Vine
Author-email: jsvine@gmail.com
License: MIT
Keywords: jupyter
Platform: UNKNOWN
Classifier: License :: OSI Approved :: MIT License
Classifier: Operating System :: OS Independent
Classifier: Programming Language :: Python :: 3
Classifier: Intended Audience :: Developers
Classifier: Topic :: Scientific/Engineering :: Information Analysis
